{
  "id": "1e6abe540bd1fbd93163ce56",
  "title": "Undang-Undang Nomor 27 Tahun 2022 tentang Pelindungan Data Pribadi",
  "type": "UU",
  "number": "27",
  "year": 2022,
  "jurisdiction": "ID",
  "sourceUrl": "https://peraturan.bpk.go.id/Details/229798/uu-no-27-tahun-2022",
  "downloadUrl": "https://peraturan.bpk.go.id/Download/224884/UU%20Nomor%2027%20Tahun%202022.pdf",
  "fetchTimestamp": "2026-07-09T02:38:54.294Z",
  "contentHash": "ed952dea04b87d14ecf037f9f324a65d50b396ddd34fc28ddf9ff014391971f6",
  "legalStatus": "ACTIVE",
  "amendedBy": null
}