{
  "id": "3c78139a9d6332ee337923f6",
  "title": "Undang-Undang Nomor 1 Tahun 2023 tentang Kitab Undang-Undang Hukum Pidana",
  "type": "UU",
  "number": "1",
  "year": 2023,
  "jurisdiction": "ID",
  "sourceUrl": "https://peraturan.bpk.go.id/Details/234935/uu-no-1-tahun-2023",
  "downloadUrl": "https://peraturan.bpk.go.id/Download/287456/UU%20Nomor%201%20Tahun%202023.pdf",
  "fetchTimestamp": "2026-07-09T02:40:24.584Z",
  "contentHash": "975fc86cfa63204ee21810cb7a99918c3a16b5fd47e58dadd9562c5ff3f1dfa0",
  "status": "ACTIVE"
}